naima_lab/__init__.py
naima_lab/py.typed
naima_lab/cli/__init__.py
naima_lab/cli/main.py
naima_lab/cli/main_nlp.py
naima_lab/interface/__init__.py
naima_lab/interface/langchain.py
naima_lab/models/__init__.py
naima_lab/models/config.py
naima_lab/models/enums.py
naima_lab/nlp/__init__.py
naima_lab/nlp/llm/train.py
naima_lab-0.1.1.dist-info/METADATA
naima_lab-0.1.1.dist-info/WHEEL
naima_lab-0.1.1.dist-info/entry_points.txt
naima_lab-0.1.1.dist-info/RECORD
